pyleoclim/__init__.py
pyleoclim/core/__init__.py
pyleoclim/core/coherences.py
pyleoclim/core/corr.py
pyleoclim/core/correns.py
pyleoclim/core/ensemblegeoseries.py
pyleoclim/core/ensembleseries.py
pyleoclim/core/ensmultivardecomp.py
pyleoclim/core/geoseries.py
pyleoclim/core/mulensgeoseries.py
pyleoclim/core/multiplegeoseries.py
pyleoclim/core/multipleseries.py
pyleoclim/core/multivardecomp.py
pyleoclim/core/psds.py
pyleoclim/core/resolutions.py
pyleoclim/core/scalograms.py
pyleoclim/core/series.py
pyleoclim/core/ssares.py
pyleoclim/core/surrogateseries.py
pyleoclim/data/EPICA_Dome_C_CO2.csv
pyleoclim/data/GISP2_d18O.csv
pyleoclim/data/HadCRUT.5.0.1.0.analysis.summary_series.global.annual.csv
pyleoclim/data/LR04.csv
pyleoclim/data/cenogrid.csv
pyleoclim/data/edc3deuttemp2007.csv
pyleoclim/data/metadata.yml
pyleoclim/data/oni.csv
pyleoclim/data/soi_data.csv
pyleoclim/data/wtc_test_data_nino_even.csv
pyleoclim/tests/__init__.py
pyleoclim/tests/conftest.py
pyleoclim/tests/examples.py
pyleoclim/tests/test_core_Coherences.py
pyleoclim/tests/test_core_CorrEns.py
pyleoclim/tests/test_core_EnsMultivarDecomp.py
pyleoclim/tests/test_core_EnsembleGeoSeries.py
pyleoclim/tests/test_core_EnsembleSeries.py
pyleoclim/tests/test_core_GeoSeries.py
pyleoclim/tests/test_core_MulEnsGeoSeries.py
pyleoclim/tests/test_core_MultipleGeoSeries.py
pyleoclim/tests/test_core_MultiplePSD.py
pyleoclim/tests/test_core_MultipleResolution.py
pyleoclim/tests/test_core_MultipleSeries.py
pyleoclim/tests/test_core_MultivariateDecomp.py
pyleoclim/tests/test_core_PSD.py
pyleoclim/tests/test_core_Resolution.py
pyleoclim/tests/test_core_SSARes.py
pyleoclim/tests/test_core_Scalogram.py
pyleoclim/tests/test_core_Series.py
pyleoclim/tests/test_core_SurrogateSeries.py
pyleoclim/tests/test_utils_tsbase.py
pyleoclim/tests/test_utils_tsmodel.py
pyleoclim/tests/test_utils_tsutils.py
pyleoclim/tests/utils/test_datasets.py
pyleoclim/utils/__init__.py
pyleoclim/utils/causality.py
pyleoclim/utils/correlation.py
pyleoclim-1.2.1.dist-info/METADATA
pyleoclim-1.2.1.dist-info/WHEEL
pyleoclim-1.2.1.dist-info/top_level.txt
pyleoclim-1.2.1.dist-info/RECORD
