Metadata-Version: 2.4
Name: pyleoclim
Version: 1.2.1
Summary: Python Package for the Analysis of Paleoclimate Data
Author: Feng Zhu, Alexander James, Jun Hu, Myron Kwan, Pratheek Athreya, Daniel Garijo, Lionel Voirol, Robert McGibbon, Dominik Stiller
Author-email: Deborah Khider <linkedearth@gmail.com>, Julien Emile-Geay <julieneg@usc.edu>
License: GPL-3.0
Project-URL: Homepage, https://github.com/linkedearth/pyleoclim_util
Project-URL: Issues, https://github.com/linkedearth/pyleoclim_util/issues
Project-URL: Documentation, https://pyleoclim-util.readthedocs.io/en/latest/
Requires-Python: >=3.11
Requires-Dist: pandas>=2.1.4
Requires-Dist: kneed>=0.7.0
Requires-Dist: statsmodels>=0.13.2
Requires-Dist: seaborn>=0.13.0
Requires-Dist: scikit-learn>=0.24.2
Requires-Dist: pathos>=0.2.8
Requires-Dist: tqdm>=4.61.2
Requires-Dist: tftb>=0.1.3
Requires-Dist: wget>=3.2
Requires-Dist: numba>=0.56
Requires-Dist: nitime>=0.9
Requires-Dist: tabulate>=0.8.9
Requires-Dist: Unidecode>=1.1.1
Requires-Dist: cartopy>=0.22.0
Requires-Dist: pyyaml
Requires-Dist: beautifulsoup4
Requires-Dist: scipy<1.16.0
Requires-Dist: requests
Requires-Dist: dill
Provides-Extra: dev
Requires-Dist: IPython; extra == "dev"
Requires-Dist: pytest; extra == "dev"
